MsgPrnt/__init__.py
MessagePrint-1.0.0.dist-info/LICENSE.txt
MessagePrint-1.0.0.dist-info/METADATA
MessagePrint-1.0.0.dist-info/WHEEL
MessagePrint-1.0.0.dist-info/top_level.txt
MessagePrint-1.0.0.dist-info/RECORD
