Metadata-Version: 2.1
Name: MessagePrint
Version: 1.0.0
Summary: Print messages to pygame screen.
Home-page: https://github.com/TheChainsawBoy/MessagePrint
Author: Jack Bennett
Author-email: Jack Bennett <jckbenn07@gmail.com>
Project-URL: Homepage, https://github.com/TheChainsawBoy/MessagePrint
Project-URL: Issues, https://github.com/TheChainsawBoy/MessagePrint
Classifier: Programming Language :: Python :: 3
Classifier: License :: OSI Approved :: GNU General Public License v3 (GPLv3)
Classifier: Operating System :: OS Independent
Requires-Python: >=3.6
License-File: LICENSE.txt
Requires-Dist: pygame >=2.0.0
